odoo/addons/l10n_ro_report_D300/README.rst
odoo/addons/l10n_ro_report_D300/__init__.py
odoo/addons/l10n_ro_report_D300/__manifest__.py
odoo/addons/l10n_ro_report_D300/demo/account_fiscal_position_data.xml
odoo/addons/l10n_ro_report_D300/demo/account_invoice_data.xml
odoo/addons/l10n_ro_report_D300/demo/account_tax_data.xml
odoo/addons/l10n_ro_report_D300/demo/account_tax_tags.xml
odoo/addons/l10n_ro_report_D300/i18n/l10n_ro_report_D300.pot
odoo/addons/l10n_ro_report_D300/report/__init__.py
odoo/addons/l10n_ro_report_D300/report/abstract_report_xlsx.py
odoo/addons/l10n_ro_report_D300/report/l10n_ro_report_D300.py
odoo/addons/l10n_ro_report_D300/report/l10n_ro_report_D300_xlsx.py
odoo/addons/l10n_ro_report_D300/static/description/icon.png
odoo/addons/l10n_ro_report_D300/static/src/css/report.css
odoo/addons/l10n_ro_report_D300/static/src/js/l10n_ro_report_d300_backend.js
odoo/addons/l10n_ro_report_D300/static/src/js/l10n_ro_report_d300_widgets.js
odoo/addons/l10n_ro_report_D300/tests/__init__.py
odoo/addons/l10n_ro_report_D300/tests/abstract_test.py
odoo/addons/l10n_ro_report_D300/tests/test_d300.py
odoo/addons/l10n_ro_report_D300/tests/test_d300_abstract.py
odoo/addons/l10n_ro_report_D300/views/l10n_ro_report_d300.xml
odoo/addons/l10n_ro_report_D300/views/l10n_ro_report_d300_template.xml
odoo/addons/l10n_ro_report_D300/views/l10n_ro_report_d300_view.xml
odoo/addons/l10n_ro_report_D300/views/layouts.xml
odoo/addons/l10n_ro_report_D300/views/report_template.xml
odoo/addons/l10n_ro_report_D300/wizards/__init__.py
odoo/addons/l10n_ro_report_D300/wizards/wizard_l10n_ro_report_d300.py
odoo/addons/l10n_ro_report_D300/wizards/wizard_l10n_ro_report_d300_view.xml
odoo11_addon_l10n_ro_report_D300-11.0.1.0.0.99.dev8.dist-info/METADATA
odoo11_addon_l10n_ro_report_D300-11.0.1.0.0.99.dev8.dist-info/WHEEL
odoo11_addon_l10n_ro_report_D300-11.0.1.0.0.99.dev8.dist-info/top_level.txt
odoo11_addon_l10n_ro_report_D300-11.0.1.0.0.99.dev8.dist-info/RECORD
